[
  {
    "Type": "SoundWave",
    "Name": "Crunch_Bite_Rip-007_wav",
    "Properties": {
      "NumChannels": 2,
      "SampleRate": 44100,
      "Duration": 2.412109
    },
    "CompressedFormatData": {
      "OGG": {
        "BulkDataFlags": "BULKDATA_ForceInlinePayload",
        "ElementCount": 36476,
        "SizeOnDisk": 36476,
        "OffsetInFile": "0x957A"
      }
    },
    "RawData": null,
    "CompressedDataGuid": "D0F56366-477EEF65-8D84828C-8337F972",
    "RunningPlatformData": null
  }
]