[
  {
    "Type": "Material",
    "Name": "M_shelfprice",
    "Properties": {
      "bUsedWithStaticLighting": true,
      "bCanMaskedBeAssumedOpaque": true,
      "StateId": "F30AD6AA-4E9D551B-9C8BD3A1-F4847C50",
      "CachedExpressionData": {
        "ReferencedTextures": [
          {
            "ObjectName": "Texture2D T_D_ShelfPriceSale",
            "ObjectPath": "Unboxed/Content/World/ToyStore/Shelf_discount/Materials/T_D_ShelfPriceSale.0"
          }
        ],
        "QualityLevelsUsed": [
          false,
          false,
          false,
          false
        ]
      }
    }
  }
]