[
  {
    "Type": "MaterialInstanceConstant",
    "Name": "MI_Tile_Green",
    "Properties": {
      "Parent": {
        "ObjectName": "Material M_Tile",
        "ObjectPath": "KevinSpel/Content/Meshes/ISW/Materials/Tiles/M_Tile.0"
      },
      "ScalarParameterValues": [
        {
          "ParameterInfo": {
            "Name": "Roughness",
            "Association": "GlobalParameter",
            "Index": -1
          },
          "ParameterValue": 0.0,
          "ExpressionGUID": "699BC511-495C5F69-7740F085-5962D484"
        },
        {
          "ParameterInfo": {
            "Name": "Tiling1",
            "Association": "GlobalParameter",
            "Index": -1
          },
          "ParameterValue": 1.0,
          "ExpressionGUID": "CB72CB21-4AD282F9-E6EBC6B9-DD92997E"
        },
        {
          "ParameterInfo": {
            "Name": "Tiling2",
            "Association": "GlobalParameter",
            "Index": -1
          },
          "ParameterValue": 1.0,
          "ExpressionGUID": "3CC07F89-469D66E8-5DAC9EB3-111A9165"
        },
        {
          "ParameterInfo": {
            "Name": "RefractionDepthBias",
            "Association": "GlobalParameter",
            "Index": -1
          },
          "ParameterValue": 0.0,
          "ExpressionGUID": "00000000-00000000-00000000-00000000"
        }
      ],
      "VectorParameterValues": [
        {
          "ParameterInfo": {
            "Name": "RidgeColor",
            "Association": "GlobalParameter",
            "Index": -1
          },
          "ParameterValue": {
            "R": 1.0,
            "G": 1.0,
            "B": 1.0,
            "A": 1.0,
            "Hex": "FFFFFFFF"
          },
          "ExpressionGUID": "24123635-4F7754A9-2FCDA7AC-2FE34FB4"
        },
        {
          "ParameterInfo": {
            "Name": "TileColor",
            "Association": "GlobalParameter",
            "Index": -1
          },
          "ParameterValue": {
            "R": 0.051108,
            "G": 1.0,
            "B": 0.0,
            "A": 1.0,
            "Hex": "FF40FF00"
          },
          "ExpressionGUID": "2A0A7F50-40C38AF3-CAB3D5A9-434D98D3"
        }
      ],
      "BasePropertyOverrides": {
        "OpacityMaskClipValue": 0.3333
      }
    }
  }
]