[
  {
    "Type": "SoundWave",
    "Name": "Shotgun_ImpactSurface03",
    "Properties": {
      "CompressionQuality": 80,
      "NumChannels": 1,
      "SampleRate": 48000,
      "bOverrideConcurrency": true,
      "ConcurrencyOverrides": {
        "ResolutionRule": "EMaxConcurrentResolutionRule::PreventNew"
      },
      "Duration": 0.22875
    },
    "CompressedFormatData": {
      "OGG": {
        "BulkDataFlags": "BULKDATA_ForceInlinePayload",
        "ElementCount": 7524,
        "SizeOnDisk": 7524,
        "OffsetInFile": "0x27DC"
      }
    },
    "RawData": null,
    "CompressedDataGuid": "069602B1-42F22778-CE4994BC-BA09A798",
    "RunningPlatformData": null
  }
]